{
    "content_name": "24054.txt.utf-8", 
    "isbn": "0671666657", 
    "language_code": "eng", 
    "author_name": "Randall Garrett", 
    "images_urls": [
        "http://www.gutenberg.org/files/24054/24054-h/images/illus1.jpg", 
        "http://www.gutenberg.org/files/24054/24054-h/images/illus2.jpg", 
        "http://www.gutenberg.org/files/24054/24054-h/images/illus3.jpg", 
        "http://www.gutenberg.org/files/24054/24054-h/images/illus4.jpg"
    ], 
    "year": 1990, 
    "images": [], 
    "id": 494, 
    "category": "Text", 
    "genres": [], 
    "copyright": "Public domain in the USA.", 
    "title": "Dead Giveaway", 
    "wikipedia": {
        "found": false
    }, 
    "average_rating": 3.45, 
    "rating_count": 186, 
    "goodreads": {
        "url": "https://www.goodreads.com/book/show/876161.Dead_Giveaway", 
        "found": true, 
        "year": 1990
    }, 
    "similar_books": [
        "Zero-Degree Murder (Search and Rescue Mystery #1)", 
        "Binary Witness (The Amy Lane Mysteries, #1)", 
        "The Case of the Killer Divorce (Jamie Quinn Mystery #2)", 
        "Perfect Game", 
        "The Coffin Trader", 
        "The Eye of Horus", 
        "Night Kill (Iris Oakley, #1)", 
        "No Room for Error (Lexi Carmichael Mystery, #7)", 
        "Kittens Can Kill (Pru Marlowe, #5)", 
        "Beat Until Stiff", 
        "Dead in the Water (Rebecca Schwartz, #4)", 
        "Every Breath You Take (Kristen Conner Mystery #2)", 
        "Murder and Moonshine (Moonshine Mystery, #1)", 
        "Killer Reunion (A Savannah Reid Mystery, #21)", 
        "How to be a Ghost (Libby Grace Mystery #1)", 
        "Scavenger Hunt (A Finny Aletter Mystery, Book 1)", 
        "Love Thy Sister (Mina's Adventures, #1)", 
        "Stalking Jack: The Hunt Begins (Madeline Donovan #1)"
    ], 
    "description": "IN THE DESOLATE REACHES OF NEVADA, ONE MAN GUARDS A BRUTAL SECRET...<br />AND HE'LL KILL FOR IT.<br />AT A PLUSH MOUNTAIN RETREAT, LIFE IS A PLEASURE.<br />THE PRICE IS MURDER.<br /><br />The Deer Creek Condos are delightfully secluded, an ultra-luxury development nestled in the mountains above Las Vegas's garish, billion-dollar carnival. There are only nine apartments, one to a floor. The owners are rich, successful and cultured, enjoying the finest of everything, with the best security money can buy...<br /><br />Now a violent winter avalanche has trapped them in the wilderness. And the residents of Deer Creek are dying, in fatal accidents that add up to homicide. Only a handful of them are left--neighbors, friends, lovers--and a old, obsessive killer. Someone whose job is death. Someone who knows every way there is to snuff a human life...<br /><br />cover art Ron Barbagallo", 
    "format": "Paperback", 
    "loc_class": "PS: Language and Literatures: American and Canadian literature", 
    "gutenberg": {
        "url": "http://www.gutenberg.org/ebooks/24054", 
        "num": 24054
    }, 
    "authors": [
        49
    ], 
    "pages": 280, 
    "language": "English", 
    "isbn13": "9780671666651", 
    "countries": [
        2
    ], 
    "release_date": "2007-12-27T00:00:00", 
    "author": 49, 
    "content_cleaned": true, 
    "classes": [
        "to-read", 
        "currently-reading", 
        "mystery", 
        "joanne-fluke", 
        "fiction", 
        "default", 
        "nook", 
        "ebooks", 
        "my-books", 
        "mystery-thriller", 
        "mysteries", 
        "mystery-suspense", 
        "ifpl", 
        "2015-reading-list", 
        "to-buy", 
        "read-in-2014", 
        "owned-pbmystery-tbr", 
        "fluke", 
        "kindle", 
        "2014-books-read", 
        "tbr-master-list", 
        "own-unread", 
        "unfinished-books", 
        "if-library", 
        "cozy-mysteries-fluke", 
        "j-fluke-various", 
        "epub-mp3", 
        "4-non-series-7-10", 
        "__dont-own-yet", 
        "books-i-ve-read", 
        "thriller", 
        "2016-reading-challenge", 
        "misc", 
        "mystery-series", 
        "i-own", 
        "suspense", 
        "kobo", 
        "gag-me-with-a-fork", 
        "but-why-is-the-rum-gone-mystery", 
        "borrrrring", 
        "baby-its-cold-outside", 
        "fluke-misc", 
        "bought-2016", 
        "scribd", 
        "pleasure", 
        "rt-10-15", 
        "books", 
        "stand-alone-2-read", 
        "dled", 
        "do-not-want", 
        "2015-150-goal", 
        "2015-challenge", 
        "2015-reading-challenge", 
        "digital-download", 
        "audio-book", 
        "amazon", 
        "ebook-library", 
        "moonreader-app-nook", 
        "books-i-want-to-read", 
        "my", 
        "out-of-the-box", 
        "guidall", 
        "catalog", 
        "adult", 
        "overdrive-not-good", 
        "cm", 
        "mystrey", 
        "shelved", 
        "tbr-2014", 
        "pub-pocket", 
        "pc-200-299", 
        "mystery-thrillers", 
        "e-book", 
        "d", 
        "c-black", 
        "author-f", 
        "romance", 
        "murder-mystery", 
        "ask-greg", 
        "mom-to-read", 
        "mystery-suspense-thriller-crime", 
        "ebrary", 
        "joan-fluk", 
        "on-oneclickdigital", 
        "wish-list", 
        "brisbane", 
        "to-find", 
        "novella", 
        "ebook", 
        "new-releases-2014-april", 
        "to-read-mystery", 
        "word-cat-editorial", 
        "authors-i-read-other-books", 
        "las-vegas-and-nevada", 
        "fav-authors-to-read", 
        "mysteries-to-read", 
        "look-for", 
        "ipad-books", 
        "fluke-joanne", 
        "paperback"
    ], 
    "content_available": true, 
    "n_authors": 1
}