{
    "content_name": "18584.txt.utf-8", 
    "isbn": "1428039937", 
    "author_name": "H. Beam Piper", 
    "images_urls": [
        "http://www.gutenberg.org/files/18584/18584-h/images/image_01.jpg", 
        "http://www.gutenberg.org/files/18584/18584-h/images/image_02.jpg", 
        "http://www.gutenberg.org/files/18584/18584-h/images/image_03.jpg", 
        "http://www.gutenberg.org/files/18584/18584-h/images/image_42.jpg"
    ], 
    "year": 1957, 
    "images": [], 
    "id": 260, 
    "category": "Text", 
    "genres": [], 
    "copyright": "Public domain in the USA.", 
    "title": "The Edge of the Knife", 
    "wikipedia": {
        "found": false
    }, 
    "average_rating": 4.75, 
    "rating_count": 92, 
    "goodreads": {
        "url": "https://www.goodreads.com/book/show/1002020.The_Edge_Of_The_Knife", 
        "found": true
    }, 
    "similar_books": [], 
    "description": "The Edge of the Knife by H. Beam Piper.", 
    "loc_class": "PS: Language and Literatures: American and Canadian literature", 
    "gutenberg": {
        "url": "http://www.gutenberg.org/ebooks/18584", 
        "num": 18584
    }, 
    "authors": [
        19
    ], 
    "isbn13": "9781428039933", 
    "language": "English", 
    "countries": [
        2
    ], 
    "release_date": "2006-06-14T00:00:00", 
    "author": 19, 
    "cover": "https://s.gr-assets.com/assets/nophoto/book/111x148-bcc042a9c91a29c1d680899eff700a03.png", 
    "content_cleaned": true, 
    "classes": [
        "to-read", 
        "sci-fi", 
        "science-fiction", 
        "fiction", 
        "short-story", 
        "scifi", 
        "kindle", 
        "time-travel", 
        "si-fi", 
        "ebook", 
        "audiobooks", 
        "short-stories", 
        "college", 
        "currently-reading", 
        "the-real-stuff", 
        "grp-favorites", 
        "audio", 
        "collection", 
        "science-fiction-fantasy", 
        "own-audiobook", 
        "my-ebooks", 
        "is-fiction", 
        "made-of-audio", 
        "15", 
        "sf", 
        "fav-authors-tr", 
        "reviewed", 
        "2015-completed", 
        "scifi-fantasy", 
        "owned", 
        "ebook_only", 
        "2014-reading-list", 
        "sff", 
        "sci", 
        "on-disk", 
        "pulp-classics", 
        "gutenberg", 
        "h-beam-piper", 
        "from-librivox", 
        "project-gutenberg", 
        "englisch", 
        "in-calibre", 
        "my-library", 
        "hugo-nebula-reading-list", 
        "vintage-scifi", 
        "american", 
        "fiction-", 
        "literary", 
        "modern", 
        "-", 
        "science", 
        "general", 
        "pdfs", 
        "2015-reading-list"
    ], 
    "content_available": true, 
    "n_authors": 1
}