{
    "content_name": "22102.txt.utf-8", 
    "isbn": "1604243430", 
    "author_name": "Alfred Coppel", 
    "images_urls": [
        "http://www.gutenberg.org/files/22102/22102-h/images/illustration.png", 
        "http://www.gutenberg.org/files/22102/22102-page-images/p115-image.png", 
        "http://www.gutenberg.org/files/22102/22102-page-images/p115.png", 
        "http://www.gutenberg.org/files/22102/22102-page-images/p116.png", 
        "http://www.gutenberg.org/files/22102/22102-page-images/p117.png", 
        "http://www.gutenberg.org/files/22102/22102-page-images/p118.png", 
        "http://www.gutenberg.org/files/22102/22102-page-images/p119.png", 
        "http://www.gutenberg.org/files/22102/22102-page-images/p120.png", 
        "http://www.gutenberg.org/files/22102/22102-page-images/p121.png", 
        "http://www.gutenberg.org/files/22102/22102-page-images/p122.png", 
        "http://www.gutenberg.org/files/22102/22102-page-images/p123.png"
    ], 
    "year": 1956, 
    "images": [], 
    "id": 858, 
    "category": "Text", 
    "genres": [], 
    "copyright": "Public domain in the USA.", 
    "title": "The Hills of Home", 
    "wikipedia": {
        "found": false
    }, 
    "average_rating": 3.76, 
    "rating_count": 19, 
    "goodreads": {
        "url": "https://www.goodreads.com/book/show/2395656.The_Hills_of_Home", 
        "found": true
    }, 
    "similar_books": [], 
    "description": "Alfred Coppel was a science fiction writer in the middle of the 20th century. He wrote adventurous stories for numerous pulp magazines. Other works by Coppel can be found under his pseudonym Robert Cham Gilman.", 
    "loc_class": "PS: Language and Literatures: American and Canadian literature", 
    "gutenberg": {
        "url": "http://www.gutenberg.org/ebooks/22102", 
        "num": 22102
    }, 
    "authors": [
        166
    ], 
    "pages": 48, 
    "language": "English", 
    "isbn13": "9781604243437", 
    "countries": [
        2
    ], 
    "release_date": "2007-07-19T00:00:00", 
    "author": 166, 
    "content_cleaned": true, 
    "classes": [
        "to-read", 
        "currently-reading", 
        "sci-fi", 
        "science-fiction", 
        "sf", 
        "male-authors", 
        "english", 
        "syfy", 
        "16", 
        "librivox-short-story-collection-11", 
        "audiobooks", 
        "short-story", 
        "books-i-disliked", 
        "christian", 
        "general", 
        "fiction", 
        "classics", 
        "my-ebooks", 
        "novel", 
        "ebook", 
        "pdfs", 
        "type-short-story", 
        "owned-books"
    ], 
    "content_available": true, 
    "n_authors": 1
}