{
    "content_name": "29060.txt.utf-8", 
    "author_name": "Miles John Breuer", 
    "images_urls": [
        "http://www.gutenberg.org/files/29060/29060-h/images/image_001.jpg"
    ], 
    "year": 1932, 
    "id": 395, 
    "category": "Text", 
    "genres": [], 
    "copyright": "Public domain in the USA.", 
    "title": "The Einstein See-Saw", 
    "wikipedia": {
        "found": false
    }, 
    "average_rating": 3.0, 
    "rating_count": 1, 
    "goodreads": {
        "url": "https://www.goodreads.com/book/show/32190093-the-einstein-see-saw", 
        "found": true, 
        "year": -1
    }, 
    "similar_books": [], 
    "loc_class": "PS: Language and Literatures: American and Canadian literature", 
    "gutenberg": {
        "url": "http://www.gutenberg.org/ebooks/29060", 
        "num": 29060
    }, 
    "authors": [
        127
    ], 
    "language": "English", 
    "countries": [
        2
    ], 
    "release_date": "2009-06-07T00:00:00", 
    "author": 127, 
    "content_cleaned": true, 
    "classes": [
        "to-read", 
        "currently-reading", 
        "unknown-publication-dates", 
        "shelf-b-authors", 
        "genre-syfi-fan-horr"
    ], 
    "content_available": true, 
    "n_authors": 1
}