{
    "bio": "C. C. Beck was born on June 8, 1910 in Zumbrota, Minnesota. Beck's father was a Lutheran minister. Beck's mother was a schoolteacher. He studied at the Chicago Academy of Fine Arts and the University of Minnesota, and also took an art correspondence course.  C. C. Beck was born on June 8, 1910 in Zumbrota, Minnesota. Beck's father was a Lutheran minister. Beck's mother was a schoolteacher. He studied at the Chicago Academy of Fine Arts and the University of Minnesota, and also took an art correspondence course.  C. C. Beck was born on June 8, 1910 in Zumbrota, Minnesota. Beck's father was a Lutheran minister. Beck's mother was a schoolteacher. He studied at the Chicago Academy of Fine Arts and the University of Minnesota, and also took an art correspondence course. ", 
    "name": "C. C. Beck", 
    "countries": [
        2
    ], 
    "wikipedia": {
        "url": "https://en.wikipedia.org/wiki/C._C._Beck", 
        "found": true
    }, 
    "n_books": 1, 
    "summary": "Charles Clarence Beck (June 8, 1910 \u2013 November 22, 1989), usually cited as C. C. Beck, was an American cartoonist and comic book artist, best known for his work on Captain Marvel at Fawcett Comics and DC Comics.\nHe was inducted into the comic book industry's Will Eisner Comic Book Hall of Fame in 1993 and the Jack Kirby Hall of Fame in 1997.", 
    "born": "1910-06-08 00:00:00", 
    "books": [
        569
    ], 
    "id": 189, 
    "died": "1989-11-22 00:00:00"
}